README.md
setup.py
Profiling_Libs.egg-info/PKG-INFO
Profiling_Libs.egg-info/SOURCES.txt
Profiling_Libs.egg-info/dependency_links.txt
Profiling_Libs.egg-info/requires.txt
Profiling_Libs.egg-info/top_level.txt
mobio/libs/kafka_consumer_lib/__init__.py
mobio/libs/kafka_consumer_lib/helpers/__init__.py
mobio/libs/kafka_consumer_lib/helpers/confulent_consumer_manager.py
mobio/libs/kafka_consumer_lib/helpers/ensure_kafka_topic.py
mobio/libs/kafka_consumer_lib/helpers/kafka_python_consumer_manager_v2.py
mobio/libs/kafka_consumer_lib/models/__init__.py
mobio/libs/kafka_consumer_lib/models/mongo/__init__.py
mobio/libs/kafka_consumer_lib/models/mongo/base_model.py
mobio/libs/kafka_consumer_lib/models/mongo/requeue_consumer_model.py